tp9/Controller.vhd
entity Controller is
    port (STB, CLK, LSB, Stop: in Bit;
          Init, Shift, Add, Done: out Bit);
end Controller;

architecture FSM of Controller is
    type States is (InitS, CheckS, AddS, ShiftS, EndS);
    signal State: States := EndS;
begin
    -- Drive control outputs based upon State
    Init  <= '1' when State = InitS else '0';
    Add   <= '1' when State = AddS  else '0';
    Shift <= '1' when State = ShiftS else '0';
    Done  <= '1' when State = EndS else '0';

    -- Determine Next State from control inputs
    StateMachine: process (CLK)
    begin
        if CLK'Event and CLK = '0' then
            case State is
                when InitS =>
                    State <= CheckS;
                when CheckS =>
                    if LSB = '1' then
                        State <= AddS;
                    elsif Stop = '0' then
                        State <= ShiftS;
                    else
                        State <= EndS;
                    end if;
                when AddS =>
                    State <= ShiftS;
                when ShiftS =>
                    State <= CheckS;
                when EndS =>
                    if STB = '1' then
                        State <= InitS;
                    end if;
            end case;
        end if;
    end process;
end FSM;

tp9/fulladder.vhd
entity fulladder is
    port (X, Y, Cin: in Bit;
          Cout, Sum: out Bit);
end fulladder;

architecture ecuacion of fulladder is
begin
    Sum <= X xor Y xor Cin;
    Cout <= (X and Y) or (X and Cin) or (Y and Cin);
end ecuacion;

tp9/Adder8.vhd
entity Adder8 is
    port (A, B: in Bit_Vector(7 downto 0);
          Cin: in Bit;
          Cout: out Bit;
          Sum: out Bit_Vector(7 downto 0));
end Adder8;

architecture Estructura of Adder8 is
    component FullAdder
        port (X, Y: in Bit;
              Cin: in Bit;
              Cout: out Bit;
              Sum: out Bit);
    end component;
    signal C: Bit_Vector(7 downto 0);
begin
    Stages: for i in 7 downto 0 generate
        LowBit: if i = 0 generate
            FA: FullAdder port map (A(0), B(0), Cin, C(0), Sum(0));
        end generate;
        OtherBits: if i /= 0 generate
            FA: FullAdder port map (A(i), B(i), C(i-1), C(i), Sum(i));
        end generate;
    end generate;
    Cout <= C(7);
end Estructura;

tp9/ShiftN.vhd
entity ShiftN is
    port (CLK: in Bit;
          CLR: in Bit;
          LD: in Bit;
          SH: in Bit;
          DIR: in Bit;
          D: in Bit_Vector;
          Q: out Bit_Vector);
begin
    assert (D'Length <= Q'Length)
        report "Entrada D no debe ser mas 'ancha' que la salida Q"
        severity Failure;
end ShiftN;

architecture Behavior of ShiftN is
begin
    Shifter: process (CLR, CLK)
        subtype InBits  is Natural range D'Length-1 downto 0;
        subtype OutBits is Natural range Q'Length-1 downto 0;
        variable State: Bit_Vector(OutBits);
    begin
        if CLR = '1' then
            State := (others => '0');
            Q <= State after 3 ns;
        elsif CLK'Event and CLK = '1' then
            if LD = '1' then
                State := (others => '0');
                State(InBits) := D;
                Q <= State after 5 ns;
            elsif SH = '1' then
                case DIR is
                    when '0' => State := '0' & State(State'Left downto 1);
                    when '1' => State := State(State'Left-1 downto 0) & '0';
                end case;
                Q <= State after 7 ns;
            end if;
        end if;
    end process;
end Behavior;

tp9/Multiplicador4.vhd
entity Multiplicador4 is 
    port (
        A,B: in Bit_Vector(3 downto 0);
        CLK,STB: in Bit;
        Producto: out Bit_Vector(7 downto 0);
        Done: out Bit
    );
end Multiplicador4;

architecture Estructura of Multiplicador4 is

    component ShiftN
        port (CLK: in Bit;
          CLR: in Bit;
          LD: in Bit;
          SH: in Bit;
          DIR: in Bit;
          D: in Bit_Vector;
          Q: out Bit_Vector);
    end component;

    component fulladder
        port (X, Y, Cin: in Bit;
          Cout, Sum: out Bit);
    end component;

    component Adder8
        port (A, B: in Bit_Vector(7 downto 0);
          Cin: in Bit;
          Cout: out Bit;
          Sum: out Bit_Vector(7 downto 0));
    end component;

    component Controller
        port (STB, CLK, LSB, Stop: in Bit;
          Init, Shift, Add, Done: out Bit);
    end component;

        signal Init, Shift, Add, Stop , LSB: Bit;
        signal outA, outB, sum, Acc : Bit_Vector(7 downto 0);
        signal A_8bit, B_8bit : Bit_Vector(7 downto 0);

    begin
        --tuve que agregar ceros para compatibilidad de 4->8bits
        A_8bit <= "0000" & A;
        B_8bit <= "0000" & B;

        RegA: ShiftN port map (
            CLK => CLK, 
            CLR => '0', 
            LD => Init, 
            SH => Shift, 
            DIR => '0', 
            D => A_8bit,  
            Q => outA
        ); -- Registro A de 8 bits

        RegB: ShiftN port map (
            CLK => CLK, 
            CLR => '0', 
            LD => Init, 
            SH => Shift, 
            DIR => '1', 
            D => B_8bit, 
            Q => outB
        ); -- Registro B de 8 bits

        Acumulador: ShiftN port map (
            CLK => CLK, 
            CLR => Init, 
            LD => Add, 
            SH => '0',
            DIR => '0',
            D => Sum, 
            Q => Acc
        ); -- Registro Acumulador de 8 bit

        Adder: Adder8 port map (
            A => outB, 
            B => Acc, 
            Cin => '0', 
            Cout => open, 
            Sum => Sum
        ); -- Sumador de 8 bits

        Stop <= not(outA(7) or outA(6) or outA(5) or outA(4) or outA(3) or outA(2) or outA(1) or outA(0));
        LSB <= outA(0);

        Controlador: Controller port map (
            STB => STB, 
            CLK => CLK, 
            LSB => LSB, 
            Stop => Stop, 
            Init => Init, 
            Shift => Shift, 
            Add => Add, 
            Done => Done
        );

        Producto <= Acc;

    end Estructura;

tp9/Test_Multiplicador4.vhd

    
    entity Test_Multiplicador4 is end;
    
    architecture Driver of Test_Multiplicador4 is 
    	component Multiplicador4
    	port (
            A,B: in Bit_Vector(3 downto 0);
            CLK,STB: in Bit;
            Producto: out Bit_Vector(7 downto 0);
            Done: out Bit
        );    	
    	end component;
    	
        signal A_tb, B_tb: Bit_Vector(3 downto 0);
        signal CLK_tb, STB_tb, Done_tb: Bit;
        signal Producto_tb: Bit_Vector(7 downto 0);

    begin

        Prueba: Multiplicador4 port map (
            A => A_tb,
            B => B_tb, 
            CLK => CLK_tb,
            STB => STB_tb,
            Producto => Producto_tb,
            Done => Done_tb
        );

        Clock : process
        begin
            work.Utils.Clock(CLK_tb, 10.416 ns, 10.416 ns);  -- 48MHz
            wait;  
        end process;

    	Stimulus: process
                variable resultado: Natural;
    		begin
    		--Multiplicar 8 x 3 y 3 x 8
    		-- Clock de 48 MHz -> 20.83ns de periodo -> 10.416 en alto y 10.416 en bajo
    		   		
            --Inicializar
            STB_tb <= '0';
            A_tb <= "0000";
            B_tb <= "0000";
            wait for 25 ns;

            -- Test 1: Multiplicar 8 × 3
            A_tb <= work.Utils.Convert(8, 4);  -- utilizo Utils.Convert
            B_tb <= work.Utils.Convert(3, 4);
            resultado := 8 * 3;
        
            wait for 25 ns;
            STB_tb <= '1';  -- Pulso de Inicio
            wait for 20 ns;
            STB_tb <= '0';  

            wait until Done_tb = '1';

            --Verifico el resultado
            assert work.Utils.Convert(Producto_tb) = resultado
            report "Error: 8 * 3 = " & Integer'image(work.Utils.Convert(Producto_tb)) & 
                   ", resultado correcto -> " & Integer'image(resultado)
            severity Error;
        
            report "Resultado fue correcto: 8 * 3 = " & Integer'image(work.Utils.Convert(Producto_tb));
            wait for 100 ns;

            -- Test 2: Multiplicar 3 × 8
            A_tb <= work.Utils.Convert(3, 4);
            B_tb <= work.Utils.Convert(8, 4);
            resultado := 3 * 8;
        
            STB_tb <= '1';
            wait for 20 ns;
            STB_tb <= '0';

            wait until Done_tb = '1';
        
            assert work.Utils.Convert(Producto_tb) = resultado
                report "Error: 3 * 8 = " & Integer'image(work.Utils.Convert(Producto_tb)) & 
                   ", resultado correcto " & Integer'image(resultado)
                severity Error;
        
            report "Resultado fue correcto: 3 * 8 = " & Integer'image(work.Utils.Convert(Producto_tb));
            wait for 100 ns;
            wait;
    	end process;
    end;

tp9/simulacion.vcd
$date
  Wed Nov  5 19:00:31 2025
$end
$version
  GHDL v0
$end
$timescale
  1 fs
$end
$scope module standard $end
$upscope $end
$scope module utils $end
$upscope $end
$scope module test_multiplicador4 $end
$var reg 4 ! a_tb[3:0] $end
$var reg 4 " b_tb[3:0] $end
$var reg 1 # clk_tb $end
$var reg 1 $ stb_tb $end
$var reg 1 % done_tb $end
$var reg 8 & producto_tb[7:0] $end
$scope module prueba $end
$var reg 4 ' a[3:0] $end
$var reg 4 ( b[3:0] $end
$var reg 1 ) clk $end
$var reg 1 * stb $end
$var reg 8 + producto[7:0] $end
$var reg 1 , done $end
$var reg 1 - init $end
$var reg 1 . shift $end
$var reg 1 / add $end
$var reg 1 0 stop $end
$var reg 1 1 lsb $end
$var reg 8 2 outa[7:0] $end
$var reg 8 3 outb[7:0] $end
$var reg 8 4 sum[7:0] $end
$var reg 8 5 acc[7:0] $end
$var reg 8 6 a_8bit[7:0] $end
$var reg 8 7 b_8bit[7:0] $end
$scope module rega $end
$var reg 1 8 clk $end
$var reg 1 9 clr $end
$var reg 1 : ld $end
$var reg 1 ; sh $end
$var reg 1 < dir $end
$var reg 8 = d[7:0] $end
$var reg 8 > q[7:0] $end
$upscope $end
$scope module regb $end
$var reg 1 ? clk $end
$var reg 1 @ clr $end
$var reg 1 A ld $end
$var reg 1 B sh $end
$var reg 1 C dir $end
$var reg 8 D d[7:0] $end
$var reg 8 E q[7:0] $end
$upscope $end
$scope module acumulador $end
$var reg 1 F clk $end
$var reg 1 G clr $end
$var reg 1 H ld $end
$var reg 1 I sh $end
$var reg 1 J dir $end
$var reg 8 K d[7:0] $end
$var reg 8 L q[7:0] $end
$upscope $end
$scope module adder $end
$var reg 8 M a[7:0] $end
$var reg 8 N b[7:0] $end
$var reg 1 O cin $end
$var reg 1 P cout $end
$var reg 8 Q sum[7:0] $end
$var reg 8 R c[7:0] $end
$scope module stages(7) $end
$scope module otherbits $end
$scope module fa $end
$var reg 1 S x $end
$var reg 1 T y $end
$var reg 1 U cin $end
$var reg 1 V cout $end
$var reg 1 W sum $end
$upscope $end
$upscope $end
$upscope $end
$scope module stages(6) $end
$scope module otherbits $end
$scope module fa $end
$var reg 1 X x $end
$var reg 1 Y y $end
$var reg 1 Z cin $end
$var reg 1 [ cout $end
$var reg 1 \ sum $end
$upscope $end
$upscope $end
$upscope $end
$scope module stages(5) $end
$scope module otherbits $end
$scope module fa $end
$var reg 1 ] x $end
$var reg 1 ^ y $end
$var reg 1 _ cin $end
$var reg 1 ` cout $end
$var reg 1 a sum $end
$upscope $end
$upscope $end
$upscope $end
$scope module stages(4) $end
$scope module otherbits $end
$scope module fa $end
$var reg 1 b x $end
$var reg 1 c y $end
$var reg 1 d cin $end
$var reg 1 e cout $end
$var reg 1 f sum $end
$upscope $end
$upscope $end
$upscope $end
$scope module stages(3) $end
$scope module otherbits $end
$scope module fa $end
$var reg 1 g x $end
$var reg 1 h y $end
$var reg 1 i cin $end
$var reg 1 j cout $end
$var reg 1 k sum $end
$upscope $end
$upscope $end
$upscope $end
$scope module stages(2) $end
$scope module otherbits $end
$scope module fa $end
$var reg 1 l x $end
$var reg 1 m y $end
$var reg 1 n cin $end
$var reg 1 o cout $end
$var reg 1 p sum $end
$upscope $end
$upscope $end
$upscope $end
$scope module stages(1) $end
$scope module otherbits $end
$scope module fa $end
$var reg 1 q x $end
$var reg 1 r y $end
$var reg 1 s cin $end
$var reg 1 t cout $end
$var reg 1 u sum $end
$upscope $end
$upscope $end
$upscope $end
$scope module stages(0) $end
$scope module lowbit $end
$scope module fa $end
$var reg 1 v x $end
$var reg 1 w y $end
$var reg 1 x cin $end
$var reg 1 y cout $end
$var reg 1 z sum $end
$upscope $end
$upscope $end
$upscope $end
$upscope $end
$scope module controlador $end
$var reg 1 { stb $end
$var reg 1 | clk $end
$var reg 1 } lsb $end
$var reg 1 !" stop $end
$var reg 1 "" init $end
$var reg 1 #" shift $end
$var reg 1 $" add $end
$var reg 1 %" done $end
$comment state is not handled $end
$upscope $end
$upscope $end
$upscope $end
$enddefinitions $end
#0
b0000 !
b0000 "
0#
0$
1%
b00000000 &
b0000 '
b0000 (
0)
0*
b00000000 +
1,
0-
0.
0/
10
01
b00000000 2
b00000000 3
b00000000 4
b00000000 5
b00000000 6
b00000000 7
08
09
0:
0;
0<
b00000000 =
b00000000 >
0?
0@
0A
0B
1C
b00000000 D
b00000000 E
0F
0G
0H
0I
0J
b00000000 K
b00000000 L
b00000000 M
b00000000 N
0O
0P
b00000000 Q
b00000000 R
0S
0T
0U
0V
0W
0X
0Y
0Z
0[
0\
0]
0^
0_
0`
0a
0b
0c
0d
0e
0f
0g
0h
0i
0j
0k
0l
0m
0n
0o
0p
0q
0r
0s
0t
0u
0v
0w
0x
0y
0z
0{
0|
0}
1!"
0""
0#"
0$"
1%"
#10416000
1#
1)
18
1?
1F
1|
#20832000
0#
0)
08
0?
0F
0|
#25000000
b1000 !
b0011 "
b1000 '
b0011 (
b00001000 6
b00000011 7
b00001000 =
b00000011 D
#31248000
1#
1)
18
1?
1F
1|
#41664000
0#
0)
08
0?
0F
0|
#50000000
1$
1*
1{
#52080000
1#
1)
18
1?
1F
1|
#62496000
0#
0%
0)
0,
1-
08
1:
0?
1A
0F
1G
0|
1""
0%"
#65496000
b00000000 L
#70000000
0$
0*
0{
#72912000
1#
1)
18
1?
1F
1|
#75912000
b00000000 L
#77912000
00
b00001000 2
b00000011 3
b00000011 4
b00001000 >
b00000011 E
b00000011 K
b00000011 M
b00000011 Q
1q
1u
1v
1z
0!"
#83328000
0#
0)
0-
08
0:
0?
0A
0F
0G
0|
0""
#86328000
b00000000 L
#93744000
1#
1)
18
1?
1F
1|
#104160000
0#
0)
1.
08
1;
0?
1B
0F
0|
1#"
#114576000
1#
1)
18
1?
1F
1|
#121576000
b00000100 2
b00000110 3
b00000110 4
b00000100 >
b00000110 E
b00000110 K
b00000110 M
b00000110 Q
1l
1p
0v
0z
#124992000
0#
0)
0.
08
0;
0?
0B
0F
0|
0#"
#135408000
1#
1)
18
1?
1F
1|
#145824000
0#
0)
1.
08
1;
0?
1B
0F
0|
1#"
#156240000
1#
1)
18
1?
1F
1|
#163240000
b00000010 2
b00001100 3
b00001100 4
b00000010 >
b00001100 E
b00001100 K
b00001100 M
b00001100 Q
1g
1k
0q
0u
#166656000
0#
0)
0.
08
0;
0?
0B
0F
0|
0#"
#177072000
1#
1)
18
1?
1F
1|
#187488000
0#
0)
1.
08
1;
0?
1B
0F
0|
1#"
#197904000
1#
1)
18
1?
1F
1|
#204904000
11
b00000001 2
b00011000 3
b00011000 4
b00000001 >
b00011000 E
b00011000 K
b00011000 M
b00011000 Q
1b
1f
0l
0p
1}
#208320000
0#
0)
0.
08
0;
0?
0B
0F
0|
0#"
#218736000
1#
1)
18
1?
1F
1|
#229152000
0#
0)
1/
08
0?
0F
1H
0|
1$"
#239568000
1#
1)
18
1?
1F
1|
#244568000
b00011000 &
b00011000 +
b00110000 4
b00011000 5
b00110000 K
b00011000 L
b00011000 N
b00110000 Q
b00011000 R
1_
1a
1c
1d
1e
1f
1h
1j
0k
#249984000
0#
0)
1.
0/
08
1;
0?
1B
0F
0H
0|
1#"
0$"
#260400000
1#
1)
18
1?
1F
1|
#267400000
10
01
b00000000 2
b00110000 3
b01001000 4
b00000000 >
b00110000 E
b01001000 K
b00110000 M
b01001000 Q
b00110000 R
1Z
1\
1]
1`
0a
0d
0f
0g
0j
1k
0}
1!"
#270816000
0#
0)
0.
08
0;
0?
0B
0F
0|
0#"
#281232000
1#
1)
18
1?
1F
1|
#291648000
0#
1%
0)
1,
08
0?
0F
0|
1%"
#302064000
1#
1)
18
1?
1F
1|
#312480000
0#
0)
08
0?
0F
0|
#322896000
1#
1)
18
1?
1F
1|
#333312000
0#
0)
08
0?
0F
0|
#343728000
1#
1)
18
1?
1F
1|
#354144000
0#
0)
08
0?
0F
0|
#364560000
1#
1)
18
1?
1F
1|
#374976000
0#
0)
08
0?
0F
0|
#385392000
1#
1)
18
1?
1F
1|
#391648000
b0011 !
b1000 "
1$
b0011 '
b1000 (
1*
b00000011 6
b00001000 7
b00000011 =
b00001000 D
1{
#395808000
0#
0%
0)
0,
1-
08
1:
0?
1A
0F
1G
0|
1""
0%"
#398808000
b00000000 &
b00000000 +
b00110000 4
b00000000 5
b00110000 K
b00000000 L
b00000000 N
b00110000 Q
b00000000 R
0Z
0\
0_
0`
1a
0c
0e
1f
0h
0k
#406224000
1#
1)
18
1?
1F
1|
#409224000
b00000000 L
#411224000
00
11
b00000011 2
b00001000 3
b00001000 4
b00000011 >
b00001000 E
b00001000 K
b00001000 M
b00001000 Q
0]
0a
0b
0f
1g
1k
1}
0!"
#411648000
0$
0*
0{
#416640000
0#
0)
0-
08
0:
0?
0A
0F
0G
0|
0""
#419640000
b00000000 L
#427056000
1#
1)
18
1?
1F
1|
#437472000
0#
0)
1/
08
0?
0F
1H
0|
1$"
#447888000
1#
1)
18
1?
1F
1|
#452888000
b00001000 &
b00001000 +
b00010000 4
b00001000 5
b00010000 K
b00001000 L
b00001000 N
b00010000 Q
b00001000 R
1d
1f
1h
1j
0k
#458304000
0#
0)
1.
0/
08
1;
0?
1B
0F
0H
0|
1#"
0$"
#468720000
1#
1)
18
1?
1F
1|
#475720000
b00000001 2
b00010000 3
b00011000 4
b00000001 >
b00010000 E
b00011000 K
b00010000 M
b00011000 Q
b00000000 R
0_
0a
1b
0d
0e
1f
0g
0j
1k
#479136000
0#
0)
0.
08
0;
0?
0B
0F
0|
0#"
#489552000
1#
1)
18
1?
1F
1|
#499968000
0#
0)
1/
08
0?
0F
1H
0|
1$"
#510384000
1#
1)
18
1?
1F
1|
#515384000
b00011000 &
b00011000 +
b00101000 4
b00011000 5
b00101000 K
b00011000 L
b00011000 N
b00101000 Q
b00010000 R
1_
1a
1c
1e
0f
#520800000
0#
0)
1.
0/
08
1;
0?
1B
0F
0H
0|
1#"
0$"
#531216000
1#
1)
18
1?
1F
1|
#538216000
10
01
b00000000 2
b00100000 3
b00111000 4
b00000000 >
b00100000 E
b00111000 K
b00100000 M
b00111000 Q
b00000000 R
0Z
0\
1]
0_
0`
1a
0b
0e
1f
0}
1!"
#541632000
0#
0)
0.
08
0;
0?
0B
0F
0|
0#"
#552048000
1#
1)
18
1?
1F
1|
#562464000
0#
1%
0)
1,
08
0?
0F
0|
1%"
